services/__init__.py
services/admin.py
services/apps.py
services/context_processors.py
services/models.py
services/sitemaps.py
services/translation.py
services/urls.py
services/views.py
services/migrations/0001_initial.py
services/migrations/__init__.py
services/static/js/service.js
services/templates/services/service_detail.html
services/templates/services/servicecategory_detail.html
services/templates/services/social.html
django_service-0.1.0.dist-info/LICENSE
django_service-0.1.0.dist-info/METADATA
django_service-0.1.0.dist-info/WHEEL
django_service-0.1.0.dist-info/top_level.txt
django_service-0.1.0.dist-info/RECORD
