Metadata-Version: 2.1
Name: django-service
Version: 0.1.0
Summary: Django application provide simple category/service details
Author-email: DLRSP <dlrsp.dev@gmail.com>
License: MIT License
Keywords: django,services
Classifier: Development Status :: 4 - Beta
Classifier: Intended Audience :: Developers
Classifier: License :: OSI Approved :: MIT License
Classifier: Programming Language :: Python :: 3
Classifier: Programming Language :: Python :: 3 :: Only
Classifier: Programming Language :: Python :: 3.8
Classifier: Programming Language :: Python :: 3.9
Classifier: Programming Language :: Python :: 3.10
Classifier: Programming Language :: Python :: 3.11
Classifier: Framework :: Django
Classifier: Framework :: Django :: 4.2
Classifier: Environment :: Web Environment
Classifier: Operating System :: OS Independent
Classifier: Topic :: Internet :: WWW/HTTP
Classifier: Topic :: Internet :: WWW/HTTP :: Dynamic Content
Classifier: Topic :: Internet :: WWW/HTTP :: WSGI :: Application
Classifier: Topic :: Software Development :: Libraries :: Application Frameworks
Classifier: Topic :: Software Development :: Libraries
Requires-Python: >=3.8
License-File: LICENSE
Requires-Dist: django
Requires-Dist: django-filer
Requires-Dist: django-filer-optimizer
Requires-Dist: django-modeltranslation
Requires-Dist: django-model-mixin
Requires-Dist: django-ordered-model
Requires-Dist: django-taggit==4.0.0
Requires-Dist: django-hashtag
Provides-Extra: test
Requires-Dist: coverage; extra == "test"
Requires-Dist: codecov; extra == "test"
Provides-Extra: lint
Requires-Dist: black; extra == "lint"
Requires-Dist: flake8; extra == "lint"
